src/jupyter_notebook_mcp_server/__init__.py
jupyter_notebook_mcp_server-0.1.0.dist-info/METADATA
jupyter_notebook_mcp_server-0.1.0.dist-info/WHEEL
jupyter_notebook_mcp_server-0.1.0.dist-info/entry_points.txt
jupyter_notebook_mcp_server-0.1.0.dist-info/RECORD
